tests/__init__.py
tests/conftest.py
tests/test_base.py
tests/test_fixtures.py
tests/test_import_xdo.py
xdo/__init__.py
xdo/xdo.py
python_libxdo_ng-0.1.4.dist-info/LICENSE
python_libxdo_ng-0.1.4.dist-info/METADATA
python_libxdo_ng-0.1.4.dist-info/WHEEL
python_libxdo_ng-0.1.4.dist-info/top_level.txt
python_libxdo_ng-0.1.4.dist-info/RECORD
