Metadata-Version: 2.1
Name: python-libxdo-ng
Version: 0.1.4
Summary: Python bindings for libxdo
Home-page: https://github.com/user202729/python-libxdo
Author: Samuele Santi
Author-email: samuele@samuelesanti.com
License: BSD License
Platform: UNKNOWN
Classifier: License :: OSI Approved :: BSD License
Classifier: Development Status :: 3 - Alpha
Classifier: Programming Language :: Python :: 2
Classifier: Programming Language :: Python :: 2.7
Classifier: Programming Language :: Python :: 3.4
Classifier: Programming Language :: Python :: 3.5
Classifier: Programming Language :: Python :: Implementation :: CPython
Requires-Dist: six
